odoo/addons/product_pricelist_access/README.rst
odoo/addons/product_pricelist_access/__init__.py
odoo/addons/product_pricelist_access/__manifest__.py
odoo/addons/product_pricelist_access/i18n/es.po
odoo/addons/product_pricelist_access/models/__init__.py
odoo/addons/product_pricelist_access/models/product_pricelist.py
odoo/addons/product_pricelist_access/readme/CONFIGURE.md
odoo/addons/product_pricelist_access/readme/CONTRIBUTORS.md
odoo/addons/product_pricelist_access/readme/DESCRIPTION.md
odoo/addons/product_pricelist_access/security/security.xml
odoo/addons/product_pricelist_access/static/description/icon.png
odoo/addons/product_pricelist_access/static/description/index.html
odoo/addons/product_pricelist_access/tests/__init__.py
odoo/addons/product_pricelist_access/tests/test_product_pricelist_access.py
odoo/addons/product_pricelist_access/views/product_pricelist_views.xml
odoo_addon_product_pricelist_access-17.0.1.0.0.1.dist-info/METADATA
odoo_addon_product_pricelist_access-17.0.1.0.0.1.dist-info/WHEEL
odoo_addon_product_pricelist_access-17.0.1.0.0.1.dist-info/top_level.txt
odoo_addon_product_pricelist_access-17.0.1.0.0.1.dist-info/RECORD
